pbt/__init__.py
pbt/cli.py
pbt/config.py
pbt/diff.py
pbt/git.py
pbt/lock.py
pbt/package.py
pbt/poetry.py
pbt/pypi.py
pbt/version.py
polyrepo_bt-1.9.3.dist-info/entry_points.txt
polyrepo_bt-1.9.3.dist-info/WHEEL
polyrepo_bt-1.9.3.dist-info/METADATA
polyrepo_bt-1.9.3.dist-info/RECORD
